Metadata-Version: 1.0
Name: distas
Version: 0.1
Summary: Gaussian distributions
Home-page: UNKNOWN
Author: Clement Victor
Author-email: UNKNOWN
License: UNKNOWN
Platform: UNKNOWN
